__init__.py
spatialtracker.py
holosense-0.1.0.dist-info/LICENSE
holosense-0.1.0.dist-info/METADATA
holosense-0.1.0.dist-info/WHEEL
holosense-0.1.0.dist-info/top_level.txt
holosense-0.1.0.dist-info/RECORD
