Metadata-Version: 2.1
Name: holosense
Version: 0.1.0
Summary: Depth perception and spatial localization from MediaPipe face mesh coordinates. Tracks within an inch at 5ft distance from the camera
Author-email: Bala Venkataraman <balav2k7@gmail.com>
License: Copyright <2024> <Bala Venkataraman>
Project-URL: repository, https://github.com/balavenkataraman123/Holosense_library
Project-URL: documentation, https://midnight-club-devgroup.github.io/holosense/
Keywords: AR,spatial,vision
Classifier: License :: OSI Approved :: MIT License
Classifier: Programming Language :: Python
Classifier: Programming Language :: Python :: 3
Requires-Python: >=3.7
License-File: LICENSE
Requires-Dist: numpy
Requires-Dist: mediapipe
